captcharun/__init__.py
captcharun/__version__.py
captcharun/client.py
captcharun/request.py
captcharun/task.py
captcharun/utils.py
captcharun-0.2.3.dist-info/LICENSE
captcharun-0.2.3.dist-info/WHEEL
captcharun-0.2.3.dist-info/METADATA
captcharun-0.2.3.dist-info/RECORD
