Metadata-Version: 2.1
Name: captcharun
Version: 0.2.3
Summary: CaptchaRun Official Python SDK
Home-page: https://captcha.run
License: MIT
Author: CaptchaRun
Author-email: admin@captcha.run
Requires-Python: >=3.7,<4.0
Classifier: License :: OSI Approved :: MIT License
Classifier: Programming Language :: Python :: 3
Classifier: Programming Language :: Python :: 3.10
Classifier: Programming Language :: Python :: 3.7
Classifier: Programming Language :: Python :: 3.8
Classifier: Programming Language :: Python :: 3.9
Requires-Dist: httpx (>=0.22.0,<0.23.0)
Project-URL: Repository, https://github.com/get-post-technology/captcha-run-python-sdk
